setup.py
distributions_udacity_course123/Binomialdistribution.py
distributions_udacity_course123/Gaussiandistribution.py
distributions_udacity_course123/Generaldistribution.py
distributions_udacity_course123/__init__.py
distributions_udacity_course123.egg-info/PKG-INFO
distributions_udacity_course123.egg-info/SOURCES.txt
distributions_udacity_course123.egg-info/dependency_links.txt
distributions_udacity_course123.egg-info/not-zip-safe
distributions_udacity_course123.egg-info/top_level.txt