Metadata-Version: 1.0
Name: distributions-udacity-course123
Version: 0.1
Summary: Gaussian distributions
Home-page: UNKNOWN
Author: Leonardo Nerone
Author-email: UNKNOWN
License: UNKNOWN
Platform: UNKNOWN
